MySQL/__init__.py
MySQL/database.py
MySQL/mysq_easy.py
mysql_connector_easy_python-0.1.dist-info/METADATA
mysql_connector_easy_python-0.1.dist-info/WHEEL
mysql_connector_easy_python-0.1.dist-info/top_level.txt
mysql_connector_easy_python-0.1.dist-info/RECORD
